bdist_wheel_name.py
bdist_wheel_name-0.1.0.dist-info/LICENSE
bdist_wheel_name-0.1.0.dist-info/METADATA
bdist_wheel_name-0.1.0.dist-info/WHEEL
bdist_wheel_name-0.1.0.dist-info/entry_points.txt
bdist_wheel_name-0.1.0.dist-info/top_level.txt
bdist_wheel_name-0.1.0.dist-info/RECORD
