Metadata-Version: 2.1
Name: bdist-wheel-name
Version: 0.1.0
Summary: Generate the name that bdist_wheel would use
Home-page: https://github.com/davidszotten/bdist_wheel_name
Author: UNKNOWN
Author-email: UNKNOWN
License: MIT
Platform: UNKNOWN
Requires-Dist: wheel
